Metadata-Version: 2.1
Name: cloc-plot
Version: 0.0.1
Summary: View the source code count of several project in a pie chart
Home-page: https://github.com/fin-ger/py-cloc-plot
Author: Fin Christensen
Author-email: christensen.fin@gmail.com
License: UNKNOWN
Platform: UNKNOWN
Classifier: Programming Language :: Python :: 3
Classifier: License :: OSI Approved :: MIT License
Classifier: Operating System :: OS Independent
